bingpaper.py
bingpaper-1.0.0.dist-info/DESCRIPTION.rst
bingpaper-1.0.0.dist-info/METADATA
bingpaper-1.0.0.dist-info/RECORD
bingpaper-1.0.0.dist-info/WHEEL
bingpaper-1.0.0.dist-info/entry_points.txt
bingpaper-1.0.0.dist-info/metadata.json
bingpaper-1.0.0.dist-info/top_level.txt
