Metadata-Version: 2.0
Name: bingpaper
Version: 1.0.0
Summary: Program to automatically set Bing's `Photo of the day` as your Desktop's wallpaper.
Home-page: https://github.com/guptarohit/bingpaper
Author: Rohit Gupta
License: BSD
Platform: UNKNOWN
Classifier: Development Status :: 4 - Beta
Classifier: Topic :: Utilities
Classifier: Programming Language :: Python
Classifier: Programming Language :: Python :: 3
Classifier: Programming Language :: Python :: 3.4
Classifier: Programming Language :: Python :: 3.5
Classifier: Programming Language :: Python :: 3.6
Classifier: Programming Language :: Python :: 3.7
Classifier: Operating System :: MacOS
Classifier: Operating System :: POSIX :: Linux
Classifier: Operating System :: Microsoft :: Windows
Classifier: License :: OSI Approved :: BSD License
Requires-Python: >=3.4.0
Requires-Dist: Pillow
